mypy_lsp_wrapper/__init__.py
mypy_lsp_wrapper-0.0.1.dist-info/METADATA
mypy_lsp_wrapper-0.0.1.dist-info/WHEEL
mypy_lsp_wrapper-0.0.1.dist-info/entry_points.txt
mypy_lsp_wrapper-0.0.1.dist-info/RECORD
